dsbuilder/__init__.py
dsbuilder/dataset_util.py
dsbuilder/dsbuilder.py
dsbuilder/dsdoc.py
dsbuilder/dswriter.py
dsbuilder/template_util.py
dsbuilder/version.py
dsbuilder/tests/__init__.py
dsbuilder/tests/test_dataset_util.py
dsbuilder/tests/test_dsdoc.py
dsbuilder/tests/test_dswriter.py
dsbuilder/tests/test_template_util.py
dsbuilder-0.2.dist-info/LICENSE
dsbuilder-0.2.dist-info/METADATA
dsbuilder-0.2.dist-info/WHEEL
dsbuilder-0.2.dist-info/entry_points.txt
dsbuilder-0.2.dist-info/top_level.txt
dsbuilder-0.2.dist-info/RECORD
